comfy_nodekit/__init__.py
comfy_nodekit/models.py
comfy_nodekit/nodes_to_py.py
comfy_nodekit-0.2.2.dist-info/WHEEL
comfy_nodekit-0.2.2.dist-info/METADATA
comfy_nodekit-0.2.2.dist-info/RECORD
