Metadata-Version: 2.3
Name: comfy-nodekit
Version: 0.2.2
Summary: Add your description here
Requires-Dist: pydantic>=2.12.3
Requires-Dist: requests>=2.32.5
Requires-Dist: ruff>=0.14.1
Requires-Python: >=3.12
